ModelSerializer/__init__.py
ModelSerializer/directory_tree_builder.py
ModelSerializer/model_serializer.py
test/__init__.py
test/directory_tree_builder_test.py
test/model_serializer_test.py
model_serializer-1.0.3.dist-info/LICENSE
model_serializer-1.0.3.dist-info/METADATA
model_serializer-1.0.3.dist-info/WHEEL
model_serializer-1.0.3.dist-info/top_level.txt
model_serializer-1.0.3.dist-info/RECORD
