Metadata-Version: 2.1
Name: model-serializer
Version: 1.0.3
Summary: A simple Python package for serializing and deserializing Python objects to and from JSON.
Home-page: https://github.com/ochotzas/
Author: Olger Chotza
Author-email: olgerdev@icloud.com
License: MIT
Classifier: License :: OSI Approved :: MIT License
Classifier: Programming Language :: Python :: 3
Classifier: Programming Language :: Python :: 3.9
Classifier: Programming Language :: Python :: 3.10
Classifier: Programming Language :: Python :: 3.11
Classifier: Operating System :: OS Independent
Requires-Python: >=3.9
License-File: LICENSE
